{
  "features": [
    {
      "type": "Feature",
      "properties": {
        "UID": "P059",
        "Label": "RIN fleet (2 ships) in revolt",
        "Popup": "HMIS Hindustan (sloop)<br>\nHMIS Travancore (sloop)<br>"
      },
      "geometry": {
        "coordinates": [
          66.971898,
          24.818384
        ],
        "type": "Point"
      },
      "id": "3ca3bfc393fc76f0980493251339a306"
    },
    {
      "type": "Feature",
      "properties": {
        "UID": "P083",
        "Label": "RIN fleet (7 ships) in revolt",
        "Popup": "HMIS Baluchistan (Minesweeper)<br>\nHMIS Bengal (Minesweeper)<br>\nHMIS Bihar (Minesweeper)<br>\nHMIS Deccan (Minesweeper)<br>\nHMIS Hong Kong (Minesweeper)<br>\nHMIS Kistna (Minesweeper)<br>\nHMIS Rohilkhand (Minesweeper)<br>"
      },
      "geometry": {
        "coordinates": [
          92.7598,
          11.626397
        ],
        "type": "Point"
      },
      "id": "81d05a11a325141d2f4ab36c7c2e7bf9"
    },
    {
      "type": "Feature",
      "properties": {
        "UID": "P033",
        "Label": "RIN fleet (36 ships) in revolt",
        "Popup": "HMIS Agra (trawler), HMIS Amritsar (trawler), HMIS Assam (corvette),<br>  HMIS Berar (trawler), HMIS Bhadravati (auxiliary vessel), HMIS Bombay<br> (fleet minesweeper), HMIS Cochin (trawler), HMIS Cuttack (trawler), HMIS<br> Dhanush (frigate), HMIS Dipavathi (auxiliary vessel), HMIS Gondwana<br>(corvette), HMIS Heera (ex-Persian Gunboat), HMIS Jumna (sloop), HMIS<br> Kalavati (auxiliary vessel), HMIS Karachi (trawler), HMIS Kathiawar<br> (fleet minesweeper), HMIS Kumaon (fleet minesweeper), HMIS Lahore<br> (trawler) HMIS Lal (ex-persian Gunboat), HMIS Madras<br> (fleet minesweeper), HMIS Madura (trawler), HMIS Mahratta (corvette), HMIS Moti<br> (ex-Persian Gonboat), HMIS Narbada (sloop), HMIS Nasik (trawler), HMIS<br> Nautilus (trawler), HMIS Neelam (ex-Persian Gunboat), HMIS Orissa, HMIS<br> Orissa (fleet minesweeper) HMIS Oudh (fleet minesweeper), HMIS Patna<br> (trawler), HMIS Poona (trawler), HMIS Punjab (fleet minesweeper), HMIS<br> Ramdas (auxiliary vessel), HMIS Rampur (trawler), HMIS Sindh (corvette)"
      },
      "geometry": {
        "coordinates": [
          72.840926,
          18.932118
        ],
        "type": "Point"
      },
      "id": "8987ac28276a451d0de31d184ed3a7e1"
    },
    {
      "type": "Feature",
      "properties": {
        "UID": "P070",
        "Label": "RIN fleet (2 ships) in revolt",
        "Popup": "HMIS Baroda<br>\nHMIS Kukri (Frigate)<br>"
      },
      "geometry": {
        "coordinates": [
          76.264643,
          9.95346
        ],
        "type": "Point"
      },
      "id": "c4b297ac10ea3e569200f8a3b692795b"
    },
    {
      "type": "Feature",
      "properties": {
        "UID": "P073",
        "Label": "RIN fleet (3 ships) in revolt",
        "Popup": "HMIS Ahmedabad<br>\nHMIS Shillong<br>\nHMIS Sonavati<br>"
      },
      "geometry": {
        "coordinates": [
          83.316793,
          17.667439
        ],
        "type": "Point"
      },
      "id": "d3fd74a4cd47c58cdddc594f769a4509"
    },
    {
      "type": "Feature",
      "properties": {
        "UID": "P027",
        "Label": "RIN fleet (3 ships) in revolt",
        "Popup": "HMIS Clive (old sloop)<br>\nHMIS Khyber<br>\nHMIS Lawrence (old sloop)<br>"
      },
      "geometry": {
        "coordinates": [
          72.834688,
          18.91922
        ],
        "type": "Point"
      },
      "id": "dc31672435bc9a60c233d7605de5ec26"
    }
  ],
  "type": "FeatureCollection"
}